odoo/addons/hr_study/README.rst
odoo/addons/hr_study/__init__.py
odoo/addons/hr_study/__manifest__.py
odoo/addons/hr_study/demo/hr_study.xml
odoo/addons/hr_study/i18n/es.po
odoo/addons/hr_study/i18n/hr_study.pot
odoo/addons/hr_study/i18n/it.po
odoo/addons/hr_study/models/__init__.py
odoo/addons/hr_study/models/hr_employee.py
odoo/addons/hr_study/models/hr_study.py
odoo/addons/hr_study/readme/CONFIGURE.rst
odoo/addons/hr_study/readme/CONTRIBUTORS.rst
odoo/addons/hr_study/readme/DESCRIPTION.rst
odoo/addons/hr_study/readme/ROADMAP.rst
odoo/addons/hr_study/readme/USAGE.rst
odoo/addons/hr_study/security/ir.model.access.csv
odoo/addons/hr_study/security/security.xml
odoo/addons/hr_study/static/description/icon.png
odoo/addons/hr_study/static/description/index.html
odoo/addons/hr_study/tests/__init__.py
odoo/addons/hr_study/tests/test_hr_study.py
odoo/addons/hr_study/views/hr_employee_view.xml
odoo/addons/hr_study/views/hr_study_views.xml
odoo13_addon_hr_study-13.0.1.0.1.dev5.dist-info/METADATA
odoo13_addon_hr_study-13.0.1.0.1.dev5.dist-info/WHEEL
odoo13_addon_hr_study-13.0.1.0.1.dev5.dist-info/top_level.txt
odoo13_addon_hr_study-13.0.1.0.1.dev5.dist-info/RECORD
